{"name":"Code-Ordinances","tagline":"City of Boston Code - Ordinances","body":"## Welcome to the City of Boston GitHub Repository for Municipal Ordinances.\r\n\r\nThis page will come online soon.  In the meantime, please check the <a href=\"https://github.com/CityOfBoston/Code-Ordinances/blob/master/README.md\">Master Branch of this GitHub Repository</a> for up to date versions of relevant files.  \r\n\r\n","google":"","note":"Don't delete this file! It's used internally to help with page regeneration."}